{"Cik":1498382,"EntityName":"Kintara Therapeutics, Inc.","Facts":{"us-gaap":{"NetIncomeLoss":{"Units":{"Usd":[{"Form":"10-Q","Frame":"CY2010Q3","Val":-7910},{"Form":"10-K","Frame":null,"Val":-108759},{"Form":"10-Q","Frame":null,"Val":-22478},{"Form":"10-Q","Frame":"CY2010Q4","Val":-14568},{"Form":"10-Q/A","Frame":null,"Val":-26305},{"Form":"10-Q/A","Frame":"CY2011Q1","Val":-3827},{"Form":"10-K/A","Frame":null,"Val":-33136},{"Form":"10-K/A","Frame":"CY2011Q2","Val":-6831},{"Form":"10-Q","Frame":null,"Val":-42576},{"Form":"10-Q","Frame":null,"Val":-3858},{"Form":"10-Q/A","Frame":"CY2011Q3","Val":-3858},{"Form":"10-Q","Frame":null,"Val":-53492},{"Form":"10-K","Frame":"CY2011","Val":-1333011},{"Form":"10-Q","Frame":null,"Val":-14774},{"Form":"10-Q","Frame":null,"Val":-14774},{"Form":"10-Q","Frame":null,"Val":-10916},{"Form":"10-Q","Frame":"CY2011Q4","Val":-10916},{"Form":"10-Q/A","Frame":null,"Val":-56621},{"Form":"10-Q/A","Frame":null,"Val":-17903},{"Form":"10-Q/A","Frame":null,"Val":-3129},{"Form":"10-Q","Frame":"CY2012Q1","Val":-411535},{"Form":"10-K/A","Frame":null,"Val":-57603},{"Form":"10-K/A","Frame":null,"Val":-18885},{"Form":"10-Q","Frame":null,"Val":-1549261},{"Form":"10-K/A","Frame":null,"Val":-982},{"Form":"10-Q","Frame":"CY2012Q2","Val":-1137726},{"Form":"10-Q/A","Frame":null,"Val":-61758},{"Form":"10-Q","Frame":null,"Val":-1977084},{"Form":"10-Q/A","Frame":null,"Val":-4155},{"Form":"10-Q","Frame":"CY2012Q3","Val":-427825},{"Form":"10-Q","Frame":null,"Val":-65008},{"Form":"10-K","Frame":null,"Val":-2400363},{"Form":"10-KT","Frame":"CY2012","Val":-2400363},{"Form":"10-Q","Frame":null,"Val":-7405},{"Form":"10-Q","Frame":"CY2012Q4","Val":-3250},{"Form":"10-Q","Frame":null,"Val":-65008},{"Form":"10-Q","Frame":null,"Val":-11247452},{"Form":"10-Q","Frame":null,"Val":-7405319},{"Form":"10-Q","Frame":"CY2013Q1","Val":-7405319},{"Form":"10-Q","Frame":null,"Val":-18061078},{"Form":"10-Q","Frame":null,"Val":-14218945},{"Form":"10-KT","Frame":null,"Val":-14218945},{"Form":"10-Q","Frame":"CY2013Q2","Val":-6813626},{"Form":"10-Q","Frame":null,"Val":-11266846},{"Form":"10-Q","Frame":null,"Val":-7424713},{"Form":"10-Q","Frame":null,"Val":6794232},{"Form":"10-Q","Frame":"CY2013Q3","Val":-6794232},{"Form":"10-K","Frame":null,"Val":-12132822},{"Form":"10-K","Frame":null,"Val":-8290689},{"Form":"10-KT","Frame":"CY2013","Val":-8290689},{"Form":"10-Q","Frame":null,"Val":-5928256},{"Form":"10-Q","Frame":"CY2013Q4","Val":865976},{"Form":"10-Q","Frame":null,"Val":-15331429},{"Form":"10-Q","Frame":null,"Val":2729649},{"Form":"10-Q","Frame":"CY2014Q1","Val":-3198607},{"Form":"10-K","Frame":null,"Val":3129348},{"Form":"10-K/A","Frame":"CY2014","Val":6358408},{"Form":"10-KT","Frame":null,"Val":-2798908},{"Form":"10-Q","Frame":null,"Val":1322361},{"Form":"10-Q","Frame":"CY2014Q3","Val":-1516736},{"Form":"10-Q","Frame":null,"Val":2399120},{"Form":"10-Q","Frame":null,"Val":-2136369},{"Form":"10-Q","Frame":null,"Val":1076759},{"Form":"10-Q","Frame":"CY2014Q4","Val":-619633},{"Form":"10-Q","Frame":null,"Val":-4048256},{"Form":"10-Q","Frame":null,"Val":-4223087},{"Form":"10-K","Frame":null,"Val":174831},{"Form":"10-Q","Frame":null,"Val":2086719},{"Form":"10-K","Frame":"CY2015Q1","Val":437583},{"Form":"10-K","Frame":null,"Val":-4796030},{"Form":"10-K/A","Frame":null,"Val":-4347767},{"Form":"10-Q","Frame":null,"Val":-4347767},{"Form":"10-Q","Frame":null,"Val":-4347767},{"Form":"10-K","Frame":"CY2015","Val":-4347767},{"Form":"10-Q","Frame":null,"Val":-1621388},{"Form":"10-Q","Frame":"CY2015Q3","Val":-1621388},{"Form":"10-Q","Frame":null,"Val":-4268078},{"Form":"10-Q","Frame":null,"Val":-4268078},{"Form":"10-Q","Frame":null,"Val":-5408479},{"Form":"10-Q","Frame":null,"Val":-5408479},{"Form":"10-K","Frame":null,"Val":-8864864},{"Form":"10-K","Frame":"CY2016","Val":8864864},{"Form":"10-Q","Frame":null,"Val":-2290339},{"Form":"10-Q","Frame":"CY2016Q3","Val":-2290339},{"Form":"10-Q","Frame":null,"Val":-3612312},{"Form":"10-Q","Frame":null,"Val":-3612312},{"Form":"10-Q","Frame":"CY2016Q4","Val":-1321973},{"Form":"10-Q","Frame":null,"Val":-5480772},{"Form":"10-Q","Frame":null,"Val":-5480772},{"Form":"10-Q","Frame":null,"Val":1868460},{"Form":"10-Q","Frame":"CY2017Q1","Val":-1868460},{"Form":"10-K","Frame":null,"Val":8081764},{"Form":"10-K","Frame":null,"Val":8081764},{"Form":"8-K","Frame":"CY2017","Val":-8081764},{"Form":"10-Q","Frame":null,"Val":-2666406},{"Form":"10-Q","Frame":"CY2017Q3","Val":-2666406},{"Form":"10-Q","Frame":null,"Val":-5828004},{"Form":"10-Q","Frame":null,"Val":-5828004},{"Form":"10-Q","Frame":null,"Val":-3161598},{"Form":"10-Q","Frame":"CY2017Q4","Val":-3161598},{"Form":"10-Q","Frame":null,"Val":-8761061},{"Form":"10-Q","Frame":null,"Val":-8761061},{"Form":"10-Q","Frame":null,"Val":-2933057},{"Form":"10-Q","Frame":"CY2018Q1","Val":-2933057},{"Form":"10-K","Frame":null,"Val":11138312},{"Form":"8-K","Frame":null,"Val":-11138312},{"Form":"10-K","Frame":"CY2018","Val":11138312},{"Form":"10-Q","Frame":null,"Val":-1991804},{"Form":"10-Q","Frame":"CY2018Q3","Val":-1991804},{"Form":"10-Q","Frame":null,"Val":-3801501},{"Form":"10-Q","Frame":null,"Val":-3801501},{"Form":"10-Q","Frame":null,"Val":-1809697},{"Form":"10-Q","Frame":"CY2018Q4","Val":-1809697},{"Form":"10-Q","Frame":null,"Val":-5465486},{"Form":"10-Q","Frame":null,"Val":-5465486},{"Form":"10-Q","Frame":null,"Val":-1663985},{"Form":"10-Q","Frame":"CY2019Q1","Val":-1663985},{"Form":"10-K","Frame":null,"Val":8048221},{"Form":"10-K","Frame":"CY2019","Val":-8048221},{"Form":"10-Q","Frame":null,"Val":-1605871},{"Form":"10-Q","Frame":"CY2019Q3","Val":-1606000},{"Form":"10-Q","Frame":null,"Val":-3345922},{"Form":"10-Q","Frame":null,"Val":-3346000},{"Form":"10-Q","Frame":null,"Val":-1740051},{"Form":"10-Q","Frame":"CY2019Q4","Val":-1740000},{"Form":"10-Q","Frame":null,"Val":-5302904},{"Form":"10-Q","Frame":null,"Val":-5303000},{"Form":"10-Q","Frame":null,"Val":-1956982},{"Form":"10-Q","Frame":"CY2020Q1","Val":-1957000},{"Form":"10-K","Frame":null,"Val":-9125916},{"Form":"10-K","Frame":"CY2020","Val":-9126000},{"Form":"10-Q","Frame":null,"Val":-19518000},{"Form":"10-Q","Frame":"CY2020Q3","Val":-19518000},{"Form":"10-Q","Frame":null,"Val":-24931000},{"Form":"10-Q","Frame":null,"Val":-24931000},{"Form":"10-Q","Frame":null,"Val":-5413000},{"Form":"10-Q","Frame":"CY2020Q4","Val":-5413000},{"Form":"10-Q","Frame":null,"Val":-31566000},{"Form":"10-Q","Frame":null,"Val":-31566000},{"Form":"10-Q","Frame":null,"Val":-6635000},{"Form":"10-Q","Frame":"CY2021Q1","Val":-6635000},{"Form":"10-K","Frame":null,"Val":-38298000},{"Form":"10-K","Frame":"CY2021","Val":-38298000},{"Form":"10-Q","Frame":null,"Val":-5966000},{"Form":"10-Q","Frame":"CY2021Q3","Val":-5966000},{"Form":"10-Q","Frame":null,"Val":-11859000},{"Form":"10-Q","Frame":null,"Val":-11859000},{"Form":"10-Q","Frame":null,"Val":-5893000},{"Form":"10-Q","Frame":"CY2021Q4","Val":-5893000},{"Form":"10-Q","Frame":null,"Val":-17215000},{"Form":"10-Q","Frame":null,"Val":-17215000},{"Form":"10-Q","Frame":null,"Val":-5356000},{"Form":"10-Q","Frame":"CY2022Q1","Val":-5356000},{"Form":"10-K","Frame":null,"Val":-22661000},{"Form":"10-K","Frame":"CY2022","Val":-22661000},{"Form":"10-Q","Frame":null,"Val":-4596000},{"Form":"10-Q","Frame":"CY2022Q3","Val":-4596000},{"Form":"10-Q","Frame":null,"Val":-8050000},{"Form":"10-Q","Frame":null,"Val":-8050000},{"Form":"10-Q","Frame":null,"Val":-3454000},{"Form":"10-Q","Frame":"CY2022Q4","Val":-3454000},{"Form":"10-Q","Frame":null,"Val":-11314000},{"Form":"10-Q","Frame":"CY2023Q1","Val":-3264000},{"Form":"10-K","Frame":"CY2023","Val":-14649000},{"Form":"10-Q","Frame":"CY2023Q3","Val":-2962000},{"Form":"10-Q","Frame":null,"Val":-3985000},{"Form":"10-Q","Frame":"CY2023Q4","Val":-1023000}]}}}}}